mincluster/__init__.py
mincluster/cluster.py
mincluster-0.0.1.dist-info/LICENSE
mincluster-0.0.1.dist-info/METADATA
mincluster-0.0.1.dist-info/WHEEL
mincluster-0.0.1.dist-info/top_level.txt
mincluster-0.0.1.dist-info/RECORD
