Metadata-Version: 2.1
Name: mincluster
Version: 0.0.1
Summary: Cluster minimization package
Author: Khushiyant
Author-email: <khushiyant2002@gmail.com>
Keywords: python,theoretical computer science,cluster
Classifier: Intended Audience :: Developers
Classifier: Programming Language :: Python :: 3
Classifier: Operating System :: Unix
Classifier: Operating System :: MacOS :: MacOS X
Classifier: Operating System :: Microsoft :: Windows
License-File: LICENSE
Requires-Dist: numpy
